didyoumean3/__init__.py
didyoumean3/__main__.py
didyoumean3/didyoumean.py
didyoumean3/test.py
didyoumean3-0.3.1.dist-info/LICENSE
didyoumean3-0.3.1.dist-info/METADATA
didyoumean3-0.3.1.dist-info/WHEEL
didyoumean3-0.3.1.dist-info/entry_points.txt
didyoumean3-0.3.1.dist-info/top_level.txt
didyoumean3-0.3.1.dist-info/RECORD
