Metadata-Version: 2.1
Name: didyoumean3
Version: 0.3.1
Summary: "Did You Mean?" suggestions for your Python3 projects.
Home-page: https://github.com/PLNech/didyoumean3
Author: PLNech
Author-email: github+didyoumean@plnech.fr
License: GPLv3
Platform: UNKNOWN
Classifier: License :: OSI Approved :: GNU General Public License v3 (GPLv3)
Classifier: Programming Language :: Python :: 3
Classifier: Programming Language :: Python :: 3.7
Requires-Dist: selenium
